{"_id":"broccoli-kitchen-sink-helpers","_rev":"20-5d5a70bfa0af3b82f11f2bc7fe8d45a0","name":"broccoli-kitchen-sink-helpers","description":"Collection of helpers that need to be extracted into separate packages","dist-tags":{"latest":"0.2.4"},"versions":{"0.1.2":{"name":"broccoli-kitchen-sink-helpers","description":"Collection of helpers that need to be extracted into separate packages","version":"0.1.2","author":{"name":"Jo Liss","email":"joliss42@gmail.com"},"main":"index.js","license":"MIT","repository":{"type":"git","url":"https://github.com/joliss/broccoli-kitchen-sink-helpers"},"dependencies":{"mkdirp":"^0.3.5","glob":"^3.2.9"},"bugs":{"url":"https://github.com/joliss/broccoli-kitchen-sink-helpers/issues"},"homepage":"https://github.com/joliss/broccoli-kitchen-sink-helpers","_id":"broccoli-kitchen-sink-helpers@0.1.2","dist":{"shasum":"064174e8a056957c19977d4124c0afff239b6e3d","tarball":"http://registry.npmjs.org/broccoli-kitchen-sink-helpers/-/broccoli-kitchen-sink-helpers-0.1.2.tgz"},"_from":".","_npmVersion":"1.4.4","_npmUser":{"name":"joliss","email":"joliss42@gmail.com"},"maintainers":[{"name":"joliss","email":"joliss42@gmail.com"}],"directories":{}},"0.2.0":{"name":"broccoli-kitchen-sink-helpers","description":"Collection of helpers that need to be extracted into separate packages","version":"0.2.0","author":{"name":"Jo Liss","email":"joliss42@gmail.com"},"main":"index.js","license":"MIT","repository":{"type":"git","url":"https://github.com/joliss/broccoli-kitchen-sink-helpers"},"dependencies":{"mkdirp":"^0.3.5","glob":"^3.2.9"},"bugs":{"url":"https://github.com/joliss/broccoli-kitchen-sink-helpers/issues"},"homepage":"https://github.com/joliss/broccoli-kitchen-sink-helpers","_id":"broccoli-kitchen-sink-helpers@0.2.0","dist":{"shasum":"656c33f8f33525cb514b1aed22675849d7d5e439","tarball":"http://registry.npmjs.org/broccoli-kitchen-sink-helpers/-/broccoli-kitchen-sink-helpers-0.2.0.tgz"},"_from":".","_npmVersion":"1.4.4","_npmUser":{"name":"joliss","email":"joliss42@gmail.com"},"maintainers":[{"name":"joliss","email":"joliss42@gmail.com"}],"directories":{}},"0.2.1":{"name":"broccoli-kitchen-sink-helpers","description":"Collection of helpers that need to be extracted into separate packages","version":"0.2.1","author":{"name":"Jo Liss","email":"joliss42@gmail.com"},"main":"index.js","license":"MIT","repository":{"type":"git","url":"https://github.com/joliss/broccoli-kitchen-sink-helpers"},"dependencies":{"mkdirp":"^0.3.5","glob":"^3.2.9"},"bugs":{"url":"https://github.com/joliss/broccoli-kitchen-sink-helpers/issues"},"homepage":"https://github.com/joliss/broccoli-kitchen-sink-helpers","_id":"broccoli-kitchen-sink-helpers@0.2.1","dist":{"shasum":"e3b3ff3f58a0e5f171dff5db7f68e06ba968f597","tarball":"http://registry.npmjs.org/broccoli-kitchen-sink-helpers/-/broccoli-kitchen-sink-helpers-0.2.1.tgz"},"_from":".","_npmVersion":"1.4.4","_npmUser":{"name":"joliss","email":"joliss42@gmail.com"},"maintainers":[{"name":"joliss","email":"joliss42@gmail.com"}],"directories":{}},"0.2.2":{"name":"broccoli-kitchen-sink-helpers","description":"Collection of helpers that need to be extracted into separate packages","version":"0.2.2","author":{"name":"Jo Liss","email":"joliss42@gmail.com"},"main":"index.js","license":"MIT","repository":{"type":"git","url":"https://github.com/joliss/broccoli-kitchen-sink-helpers"},"dependencies":{"mkdirp":"^0.3.5","glob":"^3.2.9"},"bugs":{"url":"https://github.com/joliss/broccoli-kitchen-sink-helpers/issues"},"homepage":"https://github.com/joliss/broccoli-kitchen-sink-helpers","_id":"broccoli-kitchen-sink-helpers@0.2.2","dist":{"shasum":"e98767b0e4deb6965a198afdc4a654dd6da02561","tarball":"http://registry.npmjs.org/broccoli-kitchen-sink-helpers/-/broccoli-kitchen-sink-helpers-0.2.2.tgz"},"_from":".","_npmVersion":"1.4.4","_npmUser":{"name":"joliss","email":"joliss42@gmail.com"},"maintainers":[{"name":"joliss","email":"joliss42@gmail.com"}],"directories":{}},"0.2.3":{"name":"broccoli-kitchen-sink-helpers","description":"Collection of helpers that need to be extracted into separate packages","version":"0.2.3","author":{"name":"Jo Liss","email":"joliss42@gmail.com"},"main":"index.js","license":"MIT","repository":{"type":"git","url":"https://github.com/broccolijs/broccoli-kitchen-sink-helpers"},"dependencies":{"mkdirp":"^0.3.5","glob":"^3.2.9"},"bugs":{"url":"https://github.com/broccolijs/broccoli-kitchen-sink-helpers/issues"},"homepage":"https://github.com/broccolijs/broccoli-kitchen-sink-helpers","_id":"broccoli-kitchen-sink-helpers@0.2.3","dist":{"shasum":"5743b6d1943f107d56c6b65e69ee8cd785fa640c","tarball":"http://registry.npmjs.org/broccoli-kitchen-sink-helpers/-/broccoli-kitchen-sink-helpers-0.2.3.tgz"},"_from":".","_npmVersion":"1.4.4","_npmUser":{"name":"joliss","email":"joliss42@gmail.com"},"maintainers":[{"name":"joliss","email":"joliss42@gmail.com"}],"directories":{}},"0.2.4":{"name":"broccoli-kitchen-sink-helpers","description":"Collection of helpers that need to be extracted into separate packages","version":"0.2.4","author":{"name":"Jo Liss","email":"joliss42@gmail.com"},"main":"index.js","license":"MIT","repository":{"type":"git","url":"https://github.com/broccolijs/broccoli-kitchen-sink-helpers"},"dependencies":{"mkdirp":"^0.3.5","glob":"^3.2.9"},"bugs":{"url":"https://github.com/broccolijs/broccoli-kitchen-sink-helpers/issues"},"homepage":"https://github.com/broccolijs/broccoli-kitchen-sink-helpers","_id":"broccoli-kitchen-sink-helpers@0.2.4","dist":{"shasum":"77b6642fe7854a915169b9c0ff618f74564cdfd0","tarball":"http://registry.npmjs.org/broccoli-kitchen-sink-helpers/-/broccoli-kitchen-sink-helpers-0.2.4.tgz"},"_from":".","_npmVersion":"1.4.4","_npmUser":{"name":"joliss","email":"joliss42@gmail.com"},"maintainers":[{"name":"joliss","email":"joliss42@gmail.com"}],"directories":{}}},"readme":"# broccoli-kitchen-sink-helpers\n\nA disparate collection of helper functions used by Broccoli and Broccoli\nplugins, though none of them are necessarily specific to Broccoli. Not\ndocumented, specced, tested.\n\nAll of these are yearning to be extracted into packages of their own. Takers\nare welcome.\n","maintainers":[{"name":"joliss","email":"joliss42@gmail.com"}],"time":{"modified":"2014-07-01T15:11:22.282Z","created":"2014-03-13T21:58:21.853Z","0.1.0":"2014-03-13T21:58:21.853Z","0.1.1":"2014-03-26T20:23:31.714Z","0.1.2":"2014-04-05T01:59:25.702Z","0.2.0":"2014-04-05T02:02:28.401Z","0.2.1":"2014-04-24T21:58:58.967Z","0.2.2":"2014-04-28T23:29:07.565Z","0.2.3":"2014-06-30T14:08:18.199Z","0.2.4":"2014-07-01T15:11:22.282Z"},"homepage":"https://github.com/broccolijs/broccoli-kitchen-sink-helpers","repository":{"type":"git","url":"https://github.com/broccolijs/broccoli-kitchen-sink-helpers"},"author":{"name":"Jo Liss","email":"joliss42@gmail.com"},"bugs":{"url":"https://github.com/broccolijs/broccoli-kitchen-sink-helpers/issues"},"license":"MIT","readmeFilename":"README.md","_attachments":{},"_etag":"\"5YQ40RRO693ZWD7IPWWYZZGEN\""}